[
  {
    "id": 1,
    "name": "POS Setup",
    "desc": "POS Setup for business type 1.",
    "status": 0,
    "businessType": 1,
    "amount": 3644.2,
    "currency": null
  },
  {
    "id": 2,
    "name": "Billing System Integration",
    "desc": "Billing System Integration for business type 1.",
    "status": 0,
    "businessType": 1,
    "amount": 2410.59,
    "currency": null
  },
  {
    "id": 3,
    "name": "Inventory Training",
    "desc": "Inventory Training for business type 1.",
    "status": 0,
    "businessType": 1,
    "amount": 7046.55,
    "currency": null
  },
  {
    "id": 4,
    "name": "Store Layout Design",
    "desc": "Store Layout Design for business type 1.",
    "status": 0,
    "businessType": 1,
    "amount": 8320.93,
    "currency": null
  },
  {
    "id": 5,
    "name": "Security System Installation",
    "desc": "Security System Installation for business type 1.",
    "status": 0,
    "businessType": 1,
    "amount": 9518.53,
    "currency": null
  },
  {
    "id": 6,
    "name": "Barcode Scanning Setup",
    "desc": "Barcode Scanning Setup for business type 1.",
    "status": 0,
    "businessType": 1,
    "amount": 2229.91,
    "currency": null
  },
  {
    "id": 7,
    "name": "Retail Analytics",
    "desc": "Retail Analytics for business type 1.",
    "status": 0,
    "businessType": 1,
    "amount": 3820.4,
    "currency": null
  },
  {
    "id": 8,
    "name": "Digital Payments Integration",
    "desc": "Digital Payments Integration for business type 1.",
    "status": 0,
    "businessType": 1,
    "amount": 4624.98,
    "currency": null
  },
  {
    "id": 9,
    "name": "Customer Loyalty Program",
    "desc": "Customer Loyalty Program for business type 1.",
    "status": 0,
    "businessType": 1,
    "amount": 9747.57,
    "currency": null
  },
  {
    "id": 10,
    "name": "Retail Software Support",
    "desc": "Retail Software Support for business type 1.",
    "status": 0,
    "businessType": 1,
    "amount": 3864.79,
    "currency": null
  },
  {
    "id": 11,
    "name": "Menu Planning",
    "desc": "Menu Planning for business type 2.",
    "status": 0,
    "businessType": 2,
    "amount": 6597.83,
    "currency": null
  },
  {
    "id": 12,
    "name": "Chef Training",
    "desc": "Chef Training for business type 2.",
    "status": 0,
    "businessType": 2,
    "amount": 5192.57,
    "currency": null
  },
  {
    "id": 13,
    "name": "Kitchen Cleaning",
    "desc": "Kitchen Cleaning for business type 2.",
    "status": 0,
    "businessType": 2,
    "amount": 6436.94,
    "currency": null
  },
  {
    "id": 14,
    "name": "Food Safety Inspection",
    "desc": "Food Safety Inspection for business type 2.",
    "status": 0,
    "businessType": 2,
    "amount": 2366.07,
    "currency": null
  },
  {
    "id": 15,
    "name": "Waitstaff Training",
    "desc": "Waitstaff Training for business type 2.",
    "status": 0,
    "businessType": 2,
    "amount": 1568.53,
    "currency": null
  },
  {
    "id": 16,
    "name": "POS for Restaurants",
    "desc": "POS for Restaurants for business type 2.",
    "status": 0,
    "businessType": 2,
    "amount": 5941.54,
    "currency": null
  },
  {
    "id": 17,
    "name": "Online Ordering Setup",
    "desc": "Online Ordering Setup for business type 2.",
    "status": 0,
    "businessType": 2,
    "amount": 5644.0,
    "currency": null
  },
  {
    "id": 18,
    "name": "Catering Service",
    "desc": "Catering Service for business type 2.",
    "status": 0,
    "businessType": 2,
    "amount": 751.62,
    "currency": null
  },
  {
    "id": 19,
    "name": "Recipe Costing",
    "desc": "Recipe Costing for business type 2.",
    "status": 0,
    "businessType": 2,
    "amount": 397.67,
    "currency": null
  },
  {
    "id": 20,
    "name": "Dining Area Design",
    "desc": "Dining Area Design for business type 2.",
    "status": 0,
    "businessType": 2,
    "amount": 3847.4,
    "currency": null
  },
  {
    "id": 21,
    "name": "IT Infrastructure Audit",
    "desc": "IT Infrastructure Audit for business type 3.",
    "status": 0,
    "businessType": 3,
    "amount": 5181.34,
    "currency": null
  },
  {
    "id": 22,
    "name": "Custom Software",
    "desc": "Custom Software for business type 3.",
    "status": 0,
    "businessType": 3,
    "amount": 9292.47,
    "currency": null
  },
  {
    "id": 23,
    "name": "Network Setup",
    "desc": "Network Setup for business type 3.",
    "status": 0,
    "businessType": 3,
    "amount": 4981.16,
    "currency": null
  },
  {
    "id": 24,
    "name": "Cybersecurity Audit",
    "desc": "Cybersecurity Audit for business type 3.",
    "status": 0,
    "businessType": 3,
    "amount": 294.5,
    "currency": null
  },
  {
    "id": 25,
    "name": "Cloud Migration",
    "desc": "Cloud Migration for business type 3.",
    "status": 0,
    "businessType": 3,
    "amount": 7316.22,
    "currency": null
  },
  {
    "id": 26,
    "name": "Helpdesk Setup",
    "desc": "Helpdesk Setup for business type 3.",
    "status": 0,
    "businessType": 3,
    "amount": 2859.95,
    "currency": null
  },
  {
    "id": 27,
    "name": "Data Backup Solutions",
    "desc": "Data Backup Solutions for business type 3.",
    "status": 0,
    "businessType": 3,
    "amount": 839.23,
    "currency": null
  },
  {
    "id": 28,
    "name": "Server Maintenance",
    "desc": "Server Maintenance for business type 3.",
    "status": 0,
    "businessType": 3,
    "amount": 9562.76,
    "currency": null
  },
  {
    "id": 29,
    "name": "IT Policy Design",
    "desc": "IT Policy Design for business type 3.",
    "status": 0,
    "businessType": 3,
    "amount": 5618.39,
    "currency": null
  },
  {
    "id": 30,
    "name": "Remote Support",
    "desc": "Remote Support for business type 3.",
    "status": 0,
    "businessType": 3,
    "amount": 5599.28,
    "currency": null
  },
  {
    "id": 31,
    "name": "Blueprint Drafting",
    "desc": "Blueprint Drafting for business type 4.",
    "status": 0,
    "businessType": 4,
    "amount": 7465.02,
    "currency": null
  },
  {
    "id": 32,
    "name": "Structural Engineering",
    "desc": "Structural Engineering for business type 4.",
    "status": 0,
    "businessType": 4,
    "amount": 4842.85,
    "currency": null
  },
  {
    "id": 33,
    "name": "Material Procurement",
    "desc": "Material Procurement for business type 4.",
    "status": 0,
    "businessType": 4,
    "amount": 6185.66,
    "currency": null
  },
  {
    "id": 34,
    "name": "Site Supervision",
    "desc": "Site Supervision for business type 4.",
    "status": 0,
    "businessType": 4,
    "amount": 371.8,
    "currency": null
  },
  {
    "id": 35,
    "name": "Safety Audit",
    "desc": "Safety Audit for business type 4.",
    "status": 0,
    "businessType": 4,
    "amount": 6375.4,
    "currency": null
  },
  {
    "id": 36,
    "name": "Plumbing Installation",
    "desc": "Plumbing Installation for business type 4.",
    "status": 0,
    "businessType": 4,
    "amount": 6739.73,
    "currency": null
  },
  {
    "id": 37,
    "name": "Electrical Wiring",
    "desc": "Electrical Wiring for business type 4.",
    "status": 0,
    "businessType": 4,
    "amount": 4033.76,
    "currency": null
  },
  {
    "id": 38,
    "name": "Interior Design",
    "desc": "Interior Design for business type 4.",
    "status": 0,
    "businessType": 4,
    "amount": 7571.02,
    "currency": null
  },
  {
    "id": 39,
    "name": "Land Survey",
    "desc": "Land Survey for business type 4.",
    "status": 0,
    "businessType": 4,
    "amount": 9448.95,
    "currency": null
  },
  {
    "id": 40,
    "name": "Permit Assistance",
    "desc": "Permit Assistance for business type 4.",
    "status": 0,
    "businessType": 4,
    "amount": 7571.28,
    "currency": null
  },
  {
    "id": 41,
    "name": "OPD Setup",
    "desc": "OPD Setup for business type 5.",
    "status": 0,
    "businessType": 5,
    "amount": 7990.83,
    "currency": null
  },
  {
    "id": 42,
    "name": "Patient Record Management",
    "desc": "Patient Record Management for business type 5.",
    "status": 0,
    "businessType": 5,
    "amount": 1517.61,
    "currency": null
  },
  {
    "id": 43,
    "name": "Nursing Staff Hiring",
    "desc": "Nursing Staff Hiring for business type 5.",
    "status": 0,
    "businessType": 5,
    "amount": 1909.08,
    "currency": null
  },
  {
    "id": 44,
    "name": "Medical Equipment Supply",
    "desc": "Medical Equipment Supply for business type 5.",
    "status": 0,
    "businessType": 5,
    "amount": 707.27,
    "currency": null
  },
  {
    "id": 45,
    "name": "Pathology Lab Setup",
    "desc": "Pathology Lab Setup for business type 5.",
    "status": 0,
    "businessType": 5,
    "amount": 8426.6,
    "currency": null
  },
  {
    "id": 46,
    "name": "Health Insurance Processing",
    "desc": "Health Insurance Processing for business type 5.",
    "status": 0,
    "businessType": 5,
    "amount": 961.51,
    "currency": null
  },
  {
    "id": 47,
    "name": "Appointment System Setup",
    "desc": "Appointment System Setup for business type 5.",
    "status": 0,
    "businessType": 5,
    "amount": 5461.5,
    "currency": null
  },
  {
    "id": 48,
    "name": "Basic Treatment",
    "desc": "Basic Treatment for business type 5.",
    "status": 0,
    "businessType": 5,
    "amount": 7993.88,
    "currency": null
  },
  {
    "id": 49,
    "name": "Emergency Response Plan",
    "desc": "Emergency Response Plan for business type 5.",
    "status": 0,
    "businessType": 5,
    "amount": 3336.22,
    "currency": null
  },
  {
    "id": 50,
    "name": "Clinic Branding",
    "desc": "Clinic Branding for business type 5.",
    "status": 0,
    "businessType": 5,
    "amount": 4313.25,
    "currency": null
  },
  {
    "id": 51,
    "name": "Course Curriculum Design",
    "desc": "Course Curriculum Design for business type 6.",
    "status": 0,
    "businessType": 6,
    "amount": 3236.49,
    "currency": null
  },
  {
    "id": 52,
    "name": "Online Learning Portal",
    "desc": "Online Learning Portal for business type 6.",
    "status": 0,
    "businessType": 6,
    "amount": 9602.26,
    "currency": null
  },
  {
    "id": 53,
    "name": "Instructor Hiring",
    "desc": "Instructor Hiring for business type 6.",
    "status": 0,
    "businessType": 6,
    "amount": 6622.6,
    "currency": null
  },
  {
    "id": 54,
    "name": "Student Feedback System",
    "desc": "Student Feedback System for business type 6.",
    "status": 0,
    "businessType": 6,
    "amount": 3334.23,
    "currency": null
  },
  {
    "id": 55,
    "name": "Classroom Setup",
    "desc": "Classroom Setup for business type 6.",
    "status": 0,
    "businessType": 6,
    "amount": 4853.9,
    "currency": null
  },
  {
    "id": 56,
    "name": "E-learning Module Creation",
    "desc": "E-learning Module Creation for business type 6.",
    "status": 0,
    "businessType": 6,
    "amount": 6937.99,
    "currency": null
  },
  {
    "id": 57,
    "name": "Certificate Issuance",
    "desc": "Certificate Issuance for business type 6.",
    "status": 0,
    "businessType": 6,
    "amount": 6575.64,
    "currency": null
  },
  {
    "id": 58,
    "name": "Workshop Management",
    "desc": "Workshop Management for business type 6.",
    "status": 0,
    "businessType": 6,
    "amount": 7568.06,
    "currency": null
  },
  {
    "id": 59,
    "name": "Skill Assessment",
    "desc": "Skill Assessment for business type 6.",
    "status": 0,
    "businessType": 6,
    "amount": 6598.93,
    "currency": null
  },
  {
    "id": 60,
    "name": "Training Needs Analysis",
    "desc": "Training Needs Analysis for business type 6.",
    "status": 0,
    "businessType": 6,
    "amount": 8650.96,
    "currency": null
  },
  {
    "id": 61,
    "name": "Fleet Management",
    "desc": "Fleet Management for business type 7.",
    "status": 0,
    "businessType": 7,
    "amount": 955.53,
    "currency": null
  },
  {
    "id": 62,
    "name": "Route Optimization",
    "desc": "Route Optimization for business type 7.",
    "status": 0,
    "businessType": 7,
    "amount": 2790.77,
    "currency": null
  },
  {
    "id": 63,
    "name": "Cargo Tracking",
    "desc": "Cargo Tracking for business type 7.",
    "status": 0,
    "businessType": 7,
    "amount": 3113.18,
    "currency": null
  },
  {
    "id": 64,
    "name": "Vehicle Maintenance",
    "desc": "Vehicle Maintenance for business type 7.",
    "status": 0,
    "businessType": 7,
    "amount": 6418.39,
    "currency": null
  },
  {
    "id": 65,
    "name": "Warehousing",
    "desc": "Warehousing for business type 7.",
    "status": 0,
    "businessType": 7,
    "amount": 6952.95,
    "currency": null
  },
  {
    "id": 66,
    "name": "Pickup & Drop Setup",
    "desc": "Pickup & Drop Setup for business type 7.",
    "status": 0,
    "businessType": 7,
    "amount": 9320.02,
    "currency": null
  },
  {
    "id": 67,
    "name": "Customs Clearance",
    "desc": "Customs Clearance for business type 7.",
    "status": 0,
    "businessType": 7,
    "amount": 2472.04,
    "currency": null
  },
  {
    "id": 68,
    "name": "Logistics Reporting",
    "desc": "Logistics Reporting for business type 7.",
    "status": 0,
    "businessType": 7,
    "amount": 3186.23,
    "currency": null
  },
  {
    "id": 69,
    "name": "Insurance Handling",
    "desc": "Insurance Handling for business type 7.",
    "status": 0,
    "businessType": 7,
    "amount": 9009.52,
    "currency": null
  },
  {
    "id": 70,
    "name": "Driver Training",
    "desc": "Driver Training for business type 7.",
    "status": 0,
    "businessType": 7,
    "amount": 7389.94,
    "currency": null
  },
  {
    "id": 71,
    "name": "Financial Planning",
    "desc": "Financial Planning for business type 8.",
    "status": 0,
    "businessType": 8,
    "amount": 4257.53,
    "currency": null
  },
  {
    "id": 72,
    "name": "Loan Processing",
    "desc": "Loan Processing for business type 8.",
    "status": 0,
    "businessType": 8,
    "amount": 9573.23,
    "currency": null
  },
  {
    "id": 73,
    "name": "Mutual Fund Advisory",
    "desc": "Mutual Fund Advisory for business type 8.",
    "status": 0,
    "businessType": 8,
    "amount": 8854.13,
    "currency": null
  },
  {
    "id": 74,
    "name": "Wealth Management",
    "desc": "Wealth Management for business type 8.",
    "status": 0,
    "businessType": 8,
    "amount": 478.87,
    "currency": null
  },
  {
    "id": 75,
    "name": "Budgeting Help",
    "desc": "Budgeting Help for business type 8.",
    "status": 0,
    "businessType": 8,
    "amount": 4276.46,
    "currency": null
  },
  {
    "id": 76,
    "name": "Audit Assistance",
    "desc": "Audit Assistance for business type 8.",
    "status": 0,
    "businessType": 8,
    "amount": 1424.44,
    "currency": null
  },
  {
    "id": 77,
    "name": "Risk Assessment",
    "desc": "Risk Assessment for business type 8.",
    "status": 0,
    "businessType": 8,
    "amount": 5832.13,
    "currency": null
  },
  {
    "id": 78,
    "name": "Portfolio Tracking",
    "desc": "Portfolio Tracking for business type 8.",
    "status": 0,
    "businessType": 8,
    "amount": 461.38,
    "currency": null
  },
  {
    "id": 79,
    "name": "Insurance Sale",
    "desc": "Insurance Sale for business type 8.",
    "status": 0,
    "businessType": 8,
    "amount": 1675.67,
    "currency": null
  },
  {
    "id": 80,
    "name": "Expense Management",
    "desc": "Expense Management for business type 8.",
    "status": 0,
    "businessType": 8,
    "amount": 4000.98,
    "currency": null
  },
  {
    "id": 81,
    "name": "Real Estate Photography",
    "desc": "Real Estate Photography for business type 9.",
    "status": 0,
    "businessType": 9,
    "amount": 4677.68,
    "currency": null
  },
  {
    "id": 82,
    "name": "Virtual Tours",
    "desc": "Virtual Tours for business type 9.",
    "status": 0,
    "businessType": 9,
    "amount": 6377.24,
    "currency": null
  },
  {
    "id": 83,
    "name": "Legal Verification",
    "desc": "Legal Verification for business type 9.",
    "status": 0,
    "businessType": 9,
    "amount": 9114.99,
    "currency": null
  },
  {
    "id": 84,
    "name": "Site Visits",
    "desc": "Site Visits for business type 9.",
    "status": 0,
    "businessType": 9,
    "amount": 7848.67,
    "currency": null
  },
  {
    "id": 85,
    "name": "Brokerage Setup",
    "desc": "Brokerage Setup for business type 9.",
    "status": 0,
    "businessType": 9,
    "amount": 8514.33,
    "currency": null
  },
  {
    "id": 86,
    "name": "Tenant Screening",
    "desc": "Tenant Screening for business type 9.",
    "status": 0,
    "businessType": 9,
    "amount": 1787.75,
    "currency": null
  },
  {
    "id": 87,
    "name": "Rental Agreement Drafting",
    "desc": "Rental Agreement Drafting for business type 9.",
    "status": 0,
    "businessType": 9,
    "amount": 9295.38,
    "currency": null
  },
  {
    "id": 88,
    "name": "Market Analysis",
    "desc": "Market Analysis for business type 9.",
    "status": 0,
    "businessType": 9,
    "amount": 5077.42,
    "currency": null
  },
  {
    "id": 89,
    "name": "Property Tax Assistance",
    "desc": "Property Tax Assistance for business type 9.",
    "status": 0,
    "businessType": 9,
    "amount": 8211.23,
    "currency": null
  },
  {
    "id": 90,
    "name": "Sales Negotiation",
    "desc": "Sales Negotiation for business type 9.",
    "status": 0,
    "businessType": 9,
    "amount": 2608.83,
    "currency": null
  },
  {
    "id": 91,
    "name": "Sound System Rental",
    "desc": "Sound System Rental for business type 10.",
    "status": 0,
    "businessType": 10,
    "amount": 5162.03,
    "currency": null
  },
  {
    "id": 92,
    "name": "Stage Setup",
    "desc": "Stage Setup for business type 10.",
    "status": 0,
    "businessType": 10,
    "amount": 6801.27,
    "currency": null
  },
  {
    "id": 93,
    "name": "Performer Booking",
    "desc": "Performer Booking for business type 10.",
    "status": 0,
    "businessType": 10,
    "amount": 2847.79,
    "currency": null
  },
  {
    "id": 94,
    "name": "Event Promotion",
    "desc": "Event Promotion for business type 10.",
    "status": 0,
    "businessType": 10,
    "amount": 6772.04,
    "currency": null
  },
  {
    "id": 95,
    "name": "Ticketing Platform",
    "desc": "Ticketing Platform for business type 10.",
    "status": 0,
    "businessType": 10,
    "amount": 3493.99,
    "currency": null
  },
  {
    "id": 96,
    "name": "Venue Scouting",
    "desc": "Venue Scouting for business type 10.",
    "status": 0,
    "businessType": 10,
    "amount": 8512.39,
    "currency": null
  },
  {
    "id": 97,
    "name": "Lighting Arrangement",
    "desc": "Lighting Arrangement for business type 10.",
    "status": 0,
    "businessType": 10,
    "amount": 7574.41,
    "currency": null
  },
  {
    "id": 98,
    "name": "On-site Management",
    "desc": "On-site Management for business type 10.",
    "status": 0,
    "businessType": 10,
    "amount": 9030.46,
    "currency": null
  },
  {
    "id": 99,
    "name": "VIP Hospitality",
    "desc": "VIP Hospitality for business type 10.",
    "status": 0,
    "businessType": 10,
    "amount": 3174.12,
    "currency": null
  },
  {
    "id": 100,
    "name": "Post-event Analysis",
    "desc": "Post-event Analysis for business type 10.",
    "status": 0,
    "businessType": 10,
    "amount": 3945.78,
    "currency": null
  },
  {
    "id": 101,
    "name": "Full Bike Service",
    "desc": "Full Bike Service for business type 11.",
    "status": 0,
    "businessType": 11,
    "amount": 2891.95,
    "currency": null
  },
  {
    "id": 102,
    "name": "Brake Pad Replacement",
    "desc": "Brake Pad Replacement for business type 11.",
    "status": 0,
    "businessType": 11,
    "amount": 4589.0,
    "currency": null
  },
  {
    "id": 103,
    "name": "Gear Tuning",
    "desc": "Gear Tuning for business type 11.",
    "status": 0,
    "businessType": 11,
    "amount": 7981.99,
    "currency": null
  },
  {
    "id": 104,
    "name": "Suspension Check",
    "desc": "Suspension Check for business type 11.",
    "status": 0,
    "businessType": 11,
    "amount": 383.98,
    "currency": null
  },
  {
    "id": 105,
    "name": "Chain Replacement",
    "desc": "Chain Replacement for business type 11.",
    "status": 0,
    "businessType": 11,
    "amount": 6356.34,
    "currency": null
  },
  {
    "id": 106,
    "name": "Engine Oil Refill",
    "desc": "Engine Oil Refill for business type 11.",
    "status": 0,
    "businessType": 11,
    "amount": 872.45,
    "currency": null
  },
  {
    "id": 107,
    "name": "Battery Check",
    "desc": "Battery Check for business type 11.",
    "status": 0,
    "businessType": 11,
    "amount": 1034.37,
    "currency": null
  },
  {
    "id": 108,
    "name": "Electrical Wiring Fix",
    "desc": "Electrical Wiring Fix for business type 11.",
    "status": 0,
    "businessType": 11,
    "amount": 338.71,
    "currency": null
  },
  {
    "id": 109,
    "name": "Tyre Alignment",
    "desc": "Tyre Alignment for business type 11.",
    "status": 0,
    "businessType": 11,
    "amount": 8602.72,
    "currency": null
  },
  {
    "id": 110,
    "name": "Wheel Balancing",
    "desc": "Wheel Balancing for business type 11.",
    "status": 0,
    "businessType": 11,
    "amount": 7389.97,
    "currency": null
  }
]